powa_collector/__init__.py
powa_collector/customconn.py
powa_collector/notify.py
powa_collector/options.py
powa_collector/powa_worker.py
powa_collector/snapshot.py
powa_collector/utils.py
powa_collector-1.3.1.data/scripts/powa-collector.py
powa_collector-1.3.1.dist-info/licenses/LICENSE
powa_collector-1.3.1.dist-info/METADATA
powa_collector-1.3.1.dist-info/WHEEL
powa_collector-1.3.1.dist-info/top_level.txt
powa_collector-1.3.1.dist-info/RECORD
