Metadata-Version: 2.4
Name: powa-collector
Version: 1.3.1
Summary: PoWA collector, a collector for performing remote snapshot with PoWA
Home-page: https://powa.readthedocs.io/
Author: powa-team
Author-email: rjuju123@gmail.com
License: Postgresql
Classifier: Development Status :: 5 - Production/Stable
Classifier: Programming Language :: Python :: 2
Classifier: Programming Language :: Python :: 3
Classifier: License :: OSI Approved :: PostgreSQL License
Classifier: Operating System :: OS Independent
Classifier: Intended Audience :: System Administrators
Classifier: Topic :: Database :: Front-Ends
License-File: LICENSE
Requires-Dist: psycopg2
Dynamic: author
Dynamic: author-email
Dynamic: classifier
Dynamic: description
Dynamic: description-content-type
Dynamic: home-page
Dynamic: license
Dynamic: license-file
Dynamic: requires-dist
Dynamic: summary
